PreCliPy/__init__.py
PreCliPy/disease.py
PreCliPy/drug.py
PreCliPy/link.py
PreCliPy/nct.py
PreCliPy/pmc.py
PreCliPy/data/__init__.py
PreCliPy/data/pcpy.duckdb
preclipy-0.1.7.dist-info/licenses/LICENSE
preclipy-0.1.7.dist-info/METADATA
preclipy-0.1.7.dist-info/WHEEL
preclipy-0.1.7.dist-info/top_level.txt
preclipy-0.1.7.dist-info/RECORD
