Metadata-Version: 2.4
Name: PreCliPy
Version: 0.1.7
Summary: A biomedical lookup tool for diseases, drugs, PMC articles, and NCT trials
License-File: LICENSE
Requires-Dist: pandas
Requires-Dist: duckdb
Dynamic: license-file
Dynamic: requires-dist
Dynamic: summary
